[
  {
    "id": "1",
    "employee_id": "5",
    "title": "Excellent work on the project",
    "content": "Detailed feedback content for Excellent work on the project",
    "category": "performance",
    "status": "acknowledged",
    "sender_id": "owner@company.com",
    "sender_role": "owner",
    "created_at": "2025-11-26T20:41:10.833740",
    "updated_at": "2025-12-06T20:41:10.833748",
    "communications": [],
    "acknowledged_at": "2025-12-02T20:41:10.833754"
  },
  {
    "id": "2",
    "employee_id": "5",
    "title": "Great collaboration skills",
    "content": "Detailed feedback content for Great collaboration skills",
    "category": "behavior",
    "status": "open",
    "sender_id": "owner@company.com",
    "sender_role": "owner",
    "created_at": "2025-11-25T20:41:10.833767",
    "updated_at": "2025-12-06T20:41:10.833776",
    "communications": []
  },
  {
    "id": "3",
    "employee_id": "3",
    "title": "Needs improvement in time management",
    "content": "Detailed feedback content for Needs improvement in time management",
    "category": "performance",
    "status": "open",
    "sender_id": "owner@company.com",
    "sender_role": "owner",
    "created_at": "2025-11-29T20:41:10.833784",
    "updated_at": "2025-12-06T20:41:10.833792",
    "communications": []
  },
  {
    "id": "4",
    "employee_id": "5",
    "title": "Outstanding presentation skills",
    "content": "Detailed feedback content for Outstanding presentation skills",
    "category": "skills",
    "status": "acknowledged",
    "sender_id": "owner@company.com",
    "sender_role": "owner",
    "created_at": "2025-11-30T20:41:10.833800",
    "updated_at": "2025-12-06T20:41:10.833808",
    "communications": [],
    "acknowledged_at": "2025-12-04T20:41:10.833813"
  },
  {
    "id": "5",
    "employee_id": "4",
    "title": "Keep up the good work",
    "content": "Detailed feedback content for Keep up the good work",
    "category": "general",
    "status": "acknowledged",
    "sender_id": "owner@company.com",
    "sender_role": "owner",
    "created_at": "2025-11-27T20:41:10.833825",
    "updated_at": "2025-12-06T20:41:10.833833",
    "communications": [],
    "acknowledged_at": "2025-12-01T20:41:10.833838"
  },
  {
    "id": "6",
    "employee_id": "1",
    "title": "Great progress on the Q4 project",
    "content": "John, I wanted to acknowledge your excellent work on the Q4 project. Your attention to detail and problem-solving skills have been outstanding. The code quality has improved significantly, and your collaboration with the team has been exemplary.",
    "category": "performance",
    "status": "acknowledged",
    "sender_id": "owner@company.com",
    "sender_role": "owner",
    "created_at": "2025-12-01T22:19:09.724088",
    "updated_at": "2025-12-04T22:19:09.724187",
    "communications": [],
    "acknowledged_at": "2025-12-04T22:19:09.724197"
  },
  {
    "id": "7",
    "employee_id": "1",
    "title": "Excellent code review participation",
    "content": "Your active participation in code reviews has been very helpful. Your feedback is constructive and helps improve the overall codebase quality. Keep up the great work!",
    "category": "behavior",
    "status": "open",
    "sender_id": "owner@company.com",
    "sender_role": "owner",
    "created_at": "2025-12-03T22:19:09.724208",
    "updated_at": "2025-12-12T22:06:13.734683",
    "communications": [
      {
        "id": "1",
        "sender_id": "john@company.com",
        "sender_role": "employee",
        "message": "why",
        "timestamp": "2025-12-12T22:05:58.824942"
      },
      {
        "id": "2",
        "sender_id": "john@company.com",
        "sender_role": "employee",
        "message": "for what",
        "timestamp": "2025-12-12T22:06:13.734651"
      }
    ]
  },
  {
    "id": "8",
    "employee_id": "1",
    "title": "Consider improving documentation",
    "content": "While your code is excellent, I'd like to see more comprehensive documentation. Adding detailed comments and README files would help other team members understand your work better. This is a minor area for improvement.",
    "category": "skills",
    "status": "open",
    "sender_id": "owner@company.com",
    "sender_role": "owner",
    "created_at": "2025-11-29T22:19:09.724222",
    "updated_at": "2025-11-29T22:19:09.724271",
    "communications": []
  },
  {
    "id": "9",
    "employee_id": "1",
    "title": "Outstanding problem-solving approach",
    "content": "I was impressed with how you handled the recent production issue. Your systematic approach to debugging and your clear communication throughout the resolution process was exemplary. This is exactly the kind of ownership we value.",
    "category": "performance",
    "status": "acknowledged",
    "sender_id": "owner@company.com",
    "sender_role": "owner",
    "created_at": "2025-11-26T22:19:09.724302",
    "updated_at": "2025-11-28T22:19:09.724310",
    "communications": [],
    "acknowledged_at": "2025-11-28T22:19:09.724322"
  },
  {
    "id": "1",
    "employee_id": "1",
    "title": "Need to improve communication skills",
    "content": "Please work on this",
    "category": "behavior",
    "status": "responded",
    "created_at": "2025-11-29T15:43:01.230830",
    "updated_at": "2025-11-29T15:43:01.230830"
  },
  {
    "id": "2",
    "employee_id": "1",
    "title": "Could improve time management",
    "content": "Focus on prioritization",
    "category": "behavior",
    "status": "pending_response",
    "created_at": "2025-10-26T15:43:01.230856",
    "updated_at": "2025-10-26T15:43:01.230856"
  },
  {
    "id": "3",
    "employee_id": "2",
    "title": "Need to improve communication skills",
    "content": "Please work on this",
    "category": "behavior",
    "status": "pending_response",
    "created_at": "2025-10-26T15:43:01.230892",
    "updated_at": "2025-10-26T15:43:01.230892"
  },
  {
    "id": "4",
    "employee_id": "2",
    "title": "Could improve time management",
    "content": "Focus on prioritization",
    "category": "behavior",
    "status": "responded",
    "created_at": "2025-12-06T15:43:01.230909",
    "updated_at": "2025-12-06T15:43:01.230909",
    "employee_response": "Thank you for the feedback. I will work on this."
  },
  {
    "id": "5",
    "employee_id": "3",
    "title": "Strong technical skills demonstrated",
    "content": "Keep it up",
    "category": "skills",
    "status": "responded",
    "created_at": "2025-11-24T15:43:01.230938",
    "updated_at": "2025-11-24T15:43:01.230938",
    "employee_response": "Thank you for the feedback. I will work on this."
  },
  {
    "id": "6",
    "employee_id": "3",
    "title": "Timely task completion",
    "content": "Well done",
    "category": "performance",
    "status": "responded",
    "created_at": "2025-10-21T15:43:01.230955",
    "updated_at": "2025-10-21T15:43:01.230955"
  },
  {
    "id": "7",
    "employee_id": "4",
    "title": "Strong technical skills demonstrated",
    "content": "Keep it up",
    "category": "skills",
    "status": "responded",
    "created_at": "2025-11-22T15:43:01.230982",
    "updated_at": "2025-11-22T15:43:01.230982",
    "employee_response": "Thank you for the feedback. I will work on this."
  },
  {
    "id": "8",
    "employee_id": "4",
    "title": "Could improve time management",
    "content": "Focus on prioritization",
    "category": "behavior",
    "status": "responded",
    "created_at": "2025-10-24T15:43:01.230998",
    "updated_at": "2025-10-24T15:43:01.230998",
    "employee_response": "Thank you for the feedback. I will work on this."
  },
  {
    "id": "9",
    "employee_id": "4",
    "title": "Needs more attention to detail",
    "content": "Please review work carefully",
    "category": "performance",
    "status": "responded",
    "created_at": "2025-10-26T15:43:01.231015",
    "updated_at": "2025-10-26T15:43:01.231015",
    "employee_response": "Thank you for the feedback. I will work on this."
  },
  {
    "id": "10",
    "employee_id": "5",
    "title": "Outstanding problem-solving abilities",
    "content": "Excellent",
    "category": "skills",
    "status": "responded",
    "created_at": "2025-11-04T15:43:01.231045",
    "updated_at": "2025-11-04T15:43:01.231045",
    "employee_response": "Thank you for the feedback. I will work on this."
  },
  {
    "id": "11",
    "employee_id": "5",
    "title": "Excellent work on the recent project",
    "content": "Great job!",
    "category": "performance",
    "status": "responded",
    "created_at": "2025-11-16T15:43:01.231062",
    "updated_at": "2025-11-16T15:43:01.231062",
    "employee_response": "Thank you for the feedback. I will work on this."
  },
  {
    "id": "12",
    "employee_id": "5",
    "title": "Need to improve communication skills",
    "content": "Please work on this",
    "category": "behavior",
    "status": "pending_response",
    "created_at": "2025-11-02T15:43:01.231151",
    "updated_at": "2025-11-02T15:43:01.231151"
  },
  {
    "id": "13",
    "employee_id": "5",
    "title": "Could improve time management",
    "content": "Focus on prioritization",
    "category": "behavior",
    "status": "pending_response",
    "created_at": "2025-10-16T15:43:01.231198",
    "updated_at": "2025-10-16T15:43:01.231198"
  },
  {
    "id": "14",
    "employee_id": "6",
    "title": "Could improve time management",
    "content": "Focus on prioritization",
    "category": "behavior",
    "status": "responded",
    "created_at": "2025-10-22T15:43:01.231418",
    "updated_at": "2025-10-22T15:43:01.231418",
    "employee_response": "Thank you for the feedback. I will work on this."
  },
  {
    "id": "15",
    "employee_id": "6",
    "title": "Need to improve communication skills",
    "content": "Please work on this",
    "category": "behavior",
    "status": "responded",
    "created_at": "2025-11-13T15:43:01.231445",
    "updated_at": "2025-11-13T15:43:01.231445"
  },
  {
    "id": "16",
    "employee_id": "6",
    "title": "Good collaboration with team",
    "content": "Great teamwork",
    "category": "behavior",
    "status": "pending_response",
    "created_at": "2025-11-09T15:43:01.231677",
    "updated_at": "2025-11-09T15:43:01.231677"
  },
  {
    "id": "17",
    "employee_id": "6",
    "title": "Needs more attention to detail",
    "content": "Please review work carefully",
    "category": "performance",
    "status": "closed",
    "created_at": "2025-10-29T15:43:01.231710",
    "updated_at": "2025-10-29T15:43:01.231710"
  },
  {
    "id": "18",
    "employee_id": "7",
    "title": "Outstanding problem-solving abilities",
    "content": "Excellent",
    "category": "skills",
    "status": "responded",
    "created_at": "2025-10-20T15:43:01.231751",
    "updated_at": "2025-10-20T15:43:01.231751",
    "employee_response": "Thank you for the feedback. I will work on this."
  },
  {
    "id": "19",
    "employee_id": "7",
    "title": "Good collaboration with team",
    "content": "Great teamwork",
    "category": "behavior",
    "status": "responded",
    "created_at": "2025-10-13T15:43:01.231770",
    "updated_at": "2025-10-13T15:43:01.231770"
  },
  {
    "id": "20",
    "employee_id": "7",
    "title": "Excellent work on the recent project",
    "content": "Great job!",
    "category": "performance",
    "status": "responded",
    "created_at": "2025-10-31T15:43:01.231784",
    "updated_at": "2025-10-31T15:43:01.231784",
    "employee_response": "Thank you for the feedback. I will work on this."
  },
  {
    "id": "21",
    "employee_id": "8",
    "title": "Strong technical skills demonstrated",
    "content": "Keep it up",
    "category": "skills",
    "status": "responded",
    "created_at": "2025-11-15T15:43:01.231813",
    "updated_at": "2025-11-15T15:43:01.231813",
    "employee_response": "Thank you for the feedback. I will work on this."
  },
  {
    "id": "22",
    "employee_id": "8",
    "title": "Good collaboration with team",
    "content": "Great teamwork",
    "category": "behavior",
    "status": "closed",
    "created_at": "2025-11-24T15:43:01.231829",
    "updated_at": "2025-11-24T15:43:01.231829"
  },
  {
    "id": "1",
    "employee_id": "1",
    "title": "Could improve time management",
    "content": "Focus on prioritization",
    "category": "behavior",
    "status": "responded",
    "created_at": "2025-11-29T15:43:50.245077",
    "updated_at": "2025-11-29T15:43:50.245077",
    "employee_response": "Thank you for the feedback. I will work on this."
  },
  {
    "id": "2",
    "employee_id": "1",
    "title": "Excellent work on the recent project",
    "content": "Great job!",
    "category": "performance",
    "status": "responded",
    "created_at": "2025-11-27T15:43:50.245332",
    "updated_at": "2025-11-27T15:43:50.245332",
    "employee_response": "Thank you for the feedback. I will work on this."
  },
  {
    "id": "3",
    "employee_id": "1",
    "title": "Strong technical skills demonstrated",
    "content": "Keep it up",
    "category": "skills",
    "status": "responded",
    "created_at": "2025-11-09T15:43:50.245384",
    "updated_at": "2025-11-09T15:43:50.245384",
    "employee_response": "Thank you for the feedback. I will work on this."
  },
  {
    "id": "4",
    "employee_id": "1",
    "title": "Outstanding problem-solving abilities",
    "content": "Excellent",
    "category": "skills",
    "status": "responded",
    "created_at": "2025-10-17T15:43:50.245401",
    "updated_at": "2025-10-17T15:43:50.245401"
  },
  {
    "id": "5",
    "employee_id": "1",
    "title": "Good collaboration with team",
    "content": "Great teamwork",
    "category": "behavior",
    "status": "responded",
    "created_at": "2025-11-01T15:43:50.245417",
    "updated_at": "2025-11-01T15:43:50.245417"
  },
  {
    "id": "6",
    "employee_id": "2",
    "title": "Outstanding problem-solving abilities",
    "content": "Excellent",
    "category": "skills",
    "status": "responded",
    "created_at": "2025-11-07T15:43:50.245454",
    "updated_at": "2025-11-07T15:43:50.245454",
    "employee_response": "Thank you for the feedback. I will work on this."
  },
  {
    "id": "7",
    "employee_id": "2",
    "title": "Excellent work on the recent project",
    "content": "Great job!",
    "category": "performance",
    "status": "responded",
    "created_at": "2025-10-20T15:43:50.245472",
    "updated_at": "2025-10-20T15:43:50.245472",
    "employee_response": "Thank you for the feedback. I will work on this."
  },
  {
    "id": "8",
    "employee_id": "2",
    "title": "Could improve time management",
    "content": "Focus on prioritization",
    "category": "behavior",
    "status": "responded",
    "created_at": "2025-10-12T15:43:50.245497",
    "updated_at": "2025-10-12T15:43:50.245497",
    "employee_response": "Thank you for the feedback. I will work on this."
  },
  {
    "id": "9",
    "employee_id": "3",
    "title": "Could improve time management",
    "content": "Focus on prioritization",
    "category": "behavior",
    "status": "responded",
    "created_at": "2025-10-11T15:43:50.245528",
    "updated_at": "2025-10-11T15:43:50.245528",
    "employee_response": "Thank you for the feedback. I will work on this."
  },
  {
    "id": "10",
    "employee_id": "3",
    "title": "Outstanding problem-solving abilities",
    "content": "Excellent",
    "category": "skills",
    "status": "pending_response",
    "created_at": "2025-11-05T15:43:50.245545",
    "updated_at": "2025-11-05T15:43:50.245545"
  },
  {
    "id": "11",
    "employee_id": "3",
    "title": "Excellent work on the recent project",
    "content": "Great job!",
    "category": "performance",
    "status": "pending_response",
    "created_at": "2025-11-02T15:43:50.245560",
    "updated_at": "2025-11-02T15:43:50.245560"
  },
  {
    "id": "12",
    "employee_id": "3",
    "title": "Timely task completion",
    "content": "Well done",
    "category": "performance",
    "status": "responded",
    "created_at": "2025-11-07T15:43:50.245575",
    "updated_at": "2025-11-07T15:43:50.245575",
    "employee_response": "Thank you for the feedback. I will work on this."
  },
  {
    "id": "13",
    "employee_id": "4",
    "title": "Strong technical skills demonstrated",
    "content": "Keep it up",
    "category": "skills",
    "status": "closed",
    "created_at": "2025-11-30T15:43:50.245603",
    "updated_at": "2025-11-30T15:43:50.245603"
  },
  {
    "id": "14",
    "employee_id": "4",
    "title": "Could improve time management",
    "content": "Focus on prioritization",
    "category": "behavior",
    "status": "pending_response",
    "created_at": "2025-10-28T15:43:50.245618",
    "updated_at": "2025-10-28T15:43:50.245618"
  },
  {
    "id": "15",
    "employee_id": "5",
    "title": "Needs more attention to detail",
    "content": "Please review work carefully",
    "category": "performance",
    "status": "responded",
    "created_at": "2025-11-08T15:43:50.245645",
    "updated_at": "2025-11-08T15:43:50.245645",
    "employee_response": "Thank you for the feedback. I will work on this."
  },
  {
    "id": "16",
    "employee_id": "5",
    "title": "Strong technical skills demonstrated",
    "content": "Keep it up",
    "category": "skills",
    "status": "closed",
    "created_at": "2025-11-21T15:43:50.245707",
    "updated_at": "2025-11-21T15:43:50.245707"
  },
  {
    "id": "17",
    "employee_id": "5",
    "title": "Good collaboration with team",
    "content": "Great teamwork",
    "category": "behavior",
    "status": "responded",
    "created_at": "2025-10-08T15:43:50.245726",
    "updated_at": "2025-10-08T15:43:50.245726"
  },
  {
    "id": "18",
    "employee_id": "6",
    "title": "Good collaboration with team",
    "content": "Great teamwork",
    "category": "behavior",
    "status": "responded",
    "created_at": "2025-11-10T15:43:50.245758",
    "updated_at": "2025-11-10T15:43:50.245758"
  },
  {
    "id": "19",
    "employee_id": "6",
    "title": "Strong technical skills demonstrated",
    "content": "Keep it up",
    "category": "skills",
    "status": "responded",
    "created_at": "2025-11-21T15:43:50.245774",
    "updated_at": "2025-11-21T15:43:50.245774",
    "employee_response": "Thank you for the feedback. I will work on this."
  },
  {
    "id": "20",
    "employee_id": "7",
    "title": "Good collaboration with team",
    "content": "Great teamwork",
    "category": "behavior",
    "status": "responded",
    "created_at": "2025-10-23T15:43:50.245800",
    "updated_at": "2025-10-23T15:43:50.245800",
    "employee_response": "Thank you for the feedback. I will work on this."
  },
  {
    "id": "21",
    "employee_id": "7",
    "title": "Need to improve communication skills",
    "content": "Please work on this",
    "category": "behavior",
    "status": "responded",
    "created_at": "2025-11-26T15:43:50.245816",
    "updated_at": "2025-11-26T15:43:50.245816"
  },
  {
    "id": "22",
    "employee_id": "8",
    "title": "Excellent work on the recent project",
    "content": "Great job!",
    "category": "performance",
    "status": "responded",
    "created_at": "2025-11-08T15:43:50.245841",
    "updated_at": "2025-11-08T15:43:50.245841",
    "employee_response": "Thank you for the feedback. I will work on this."
  },
  {
    "id": "23",
    "employee_id": "8",
    "title": "Could improve time management",
    "content": "Focus on prioritization",
    "category": "behavior",
    "status": "closed",
    "created_at": "2025-11-02T15:43:50.245857",
    "updated_at": "2025-11-02T15:43:50.245857"
  },
  {
    "id": "1",
    "employee_id": "1",
    "title": "Needs more attention to detail",
    "content": "Please review work carefully",
    "category": "performance",
    "status": "responded",
    "created_at": "2025-10-28T15:49:27.146119",
    "updated_at": "2025-10-28T15:49:27.146119",
    "employee_response": "Thank you for the feedback. I will work on this."
  },
  {
    "id": "2",
    "employee_id": "1",
    "title": "Need to improve communication skills",
    "content": "Please work on this",
    "category": "behavior",
    "status": "pending_response",
    "created_at": "2025-10-27T15:49:27.146145",
    "updated_at": "2025-10-27T15:49:27.146145"
  },
  {
    "id": "3",
    "employee_id": "1",
    "title": "Excellent work on the recent project",
    "content": "Great job!",
    "category": "performance",
    "status": "responded",
    "created_at": "2025-11-14T15:49:27.146167",
    "updated_at": "2025-11-14T15:49:27.146167"
  },
  {
    "id": "4",
    "employee_id": "1",
    "title": "Outstanding problem-solving abilities",
    "content": "Excellent",
    "category": "skills",
    "status": "responded",
    "created_at": "2025-10-31T15:49:27.146188",
    "updated_at": "2025-10-31T15:49:27.146188",
    "employee_response": "Thank you for the feedback. I will work on this."
  },
  {
    "id": "5",
    "employee_id": "2",
    "title": "Excellent work on the recent project",
    "content": "Great job!",
    "category": "performance",
    "status": "responded",
    "created_at": "2025-11-05T15:49:27.146224",
    "updated_at": "2025-11-05T15:49:27.146224",
    "employee_response": "Thank you for the feedback. I will work on this."
  },
  {
    "id": "6",
    "employee_id": "2",
    "title": "Outstanding problem-solving abilities",
    "content": "Excellent",
    "category": "skills",
    "status": "responded",
    "created_at": "2025-11-18T15:49:27.146243",
    "updated_at": "2025-11-18T15:49:27.146243",
    "employee_response": "Thank you for the feedback. I will work on this."
  },
  {
    "id": "7",
    "employee_id": "2",
    "title": "Good collaboration with team",
    "content": "Great teamwork",
    "category": "behavior",
    "status": "pending_response",
    "created_at": "2025-11-16T15:49:27.146259",
    "updated_at": "2025-11-16T15:49:27.146259"
  },
  {
    "id": "8",
    "employee_id": "2",
    "title": "Needs more attention to detail",
    "content": "Please review work carefully",
    "category": "performance",
    "status": "responded",
    "created_at": "2025-10-27T15:49:27.146274",
    "updated_at": "2025-10-27T15:49:27.146274",
    "employee_response": "Thank you for the feedback. I will work on this."
  },
  {
    "id": "9",
    "employee_id": "2",
    "title": "Strong technical skills demonstrated",
    "content": "Keep it up",
    "category": "skills",
    "status": "responded",
    "created_at": "2025-10-29T15:49:27.146289",
    "updated_at": "2025-10-29T15:49:27.146289"
  },
  {
    "id": "10",
    "employee_id": "3",
    "title": "Strong technical skills demonstrated",
    "content": "Keep it up",
    "category": "skills",
    "status": "responded",
    "created_at": "2025-10-30T15:49:27.146317",
    "updated_at": "2025-10-30T15:49:27.146317"
  },
  {
    "id": "11",
    "employee_id": "3",
    "title": "Need to improve communication skills",
    "content": "Please work on this",
    "category": "behavior",
    "status": "responded",
    "created_at": "2025-11-30T15:49:27.146333",
    "updated_at": "2025-11-30T15:49:27.146333",
    "employee_response": "Thank you for the feedback. I will work on this."
  },
  {
    "id": "12",
    "employee_id": "3",
    "title": "Needs more attention to detail",
    "content": "Please review work carefully",
    "category": "performance",
    "status": "responded",
    "created_at": "2025-10-15T15:49:27.146350",
    "updated_at": "2025-10-15T15:49:27.146350",
    "employee_response": "Thank you for the feedback. I will work on this."
  },
  {
    "id": "13",
    "employee_id": "4",
    "title": "Outstanding problem-solving abilities",
    "content": "Excellent",
    "category": "skills",
    "status": "pending_response",
    "created_at": "2025-11-30T15:49:27.146379",
    "updated_at": "2025-11-30T15:49:27.146379"
  },
  {
    "id": "14",
    "employee_id": "4",
    "title": "Excellent work on the recent project",
    "content": "Great job!",
    "category": "performance",
    "status": "responded",
    "created_at": "2025-11-25T15:49:27.146396",
    "updated_at": "2025-11-25T15:49:27.146396",
    "employee_response": "Thank you for the feedback. I will work on this."
  },
  {
    "id": "15",
    "employee_id": "4",
    "title": "Need to improve communication skills",
    "content": "Please work on this",
    "category": "behavior",
    "status": "responded",
    "created_at": "2025-11-15T15:49:27.146411",
    "updated_at": "2025-11-15T15:49:27.146411",
    "employee_response": "Thank you for the feedback. I will work on this."
  },
  {
    "id": "16",
    "employee_id": "4",
    "title": "Could improve time management",
    "content": "Focus on prioritization",
    "category": "behavior",
    "status": "responded",
    "created_at": "2025-10-27T15:49:27.146427",
    "updated_at": "2025-10-27T15:49:27.146427",
    "employee_response": "Thank you for the feedback. I will work on this."
  },
  {
    "id": "17",
    "employee_id": "4",
    "title": "Needs more attention to detail",
    "content": "Please review work carefully",
    "category": "performance",
    "status": "pending_response",
    "created_at": "2025-10-15T15:49:27.146449",
    "updated_at": "2025-10-15T15:49:27.146449"
  },
  {
    "id": "18",
    "employee_id": "5",
    "title": "Good collaboration with team",
    "content": "Great teamwork",
    "category": "behavior",
    "status": "responded",
    "created_at": "2025-11-06T15:49:27.146477",
    "updated_at": "2025-11-06T15:49:27.146477",
    "employee_response": "Thank you for the feedback. I will work on this."
  },
  {
    "id": "19",
    "employee_id": "5",
    "title": "Outstanding problem-solving abilities",
    "content": "Excellent",
    "category": "skills",
    "status": "closed",
    "created_at": "2025-10-22T15:49:27.146494",
    "updated_at": "2025-10-22T15:49:27.146494"
  },
  {
    "id": "20",
    "employee_id": "6",
    "title": "Could improve time management",
    "content": "Focus on prioritization",
    "category": "behavior",
    "status": "responded",
    "created_at": "2025-11-17T15:49:27.146520",
    "updated_at": "2025-11-17T15:49:27.146520"
  },
  {
    "id": "21",
    "employee_id": "6",
    "title": "Good collaboration with team",
    "content": "Great teamwork",
    "category": "behavior",
    "status": "responded",
    "created_at": "2025-11-18T15:49:27.146536",
    "updated_at": "2025-11-18T15:49:27.146536",
    "employee_response": "Thank you for the feedback. I will work on this."
  },
  {
    "id": "22",
    "employee_id": "7",
    "title": "Needs more attention to detail",
    "content": "Please review work carefully",
    "category": "performance",
    "status": "responded",
    "created_at": "2025-11-28T15:49:27.146565",
    "updated_at": "2025-11-28T15:49:27.146565"
  },
  {
    "id": "23",
    "employee_id": "7",
    "title": "Excellent work on the recent project",
    "content": "Great job!",
    "category": "performance",
    "status": "pending_response",
    "created_at": "2025-11-05T15:49:27.146581",
    "updated_at": "2025-11-05T15:49:27.146581"
  },
  {
    "id": "24",
    "employee_id": "7",
    "title": "Timely task completion",
    "content": "Well done",
    "category": "performance",
    "status": "responded",
    "created_at": "2025-11-01T15:49:27.146597",
    "updated_at": "2025-11-01T15:49:27.146597"
  },
  {
    "id": "25",
    "employee_id": "7",
    "title": "Strong technical skills demonstrated",
    "content": "Keep it up",
    "category": "skills",
    "status": "responded",
    "created_at": "2025-12-01T15:49:27.146612",
    "updated_at": "2025-12-01T15:49:27.146612"
  },
  {
    "id": "26",
    "employee_id": "8",
    "title": "Excellent work on the recent project",
    "content": "Great job!",
    "category": "performance",
    "status": "responded",
    "created_at": "2025-11-05T15:49:27.146640",
    "updated_at": "2025-11-05T15:49:27.146640",
    "employee_response": "Thank you for the feedback. I will work on this."
  },
  {
    "id": "27",
    "employee_id": "8",
    "title": "Outstanding problem-solving abilities",
    "content": "Excellent",
    "category": "skills",
    "status": "responded",
    "created_at": "2025-11-28T15:49:27.146656",
    "updated_at": "2025-11-28T15:49:27.146656",
    "employee_response": "Thank you for the feedback. I will work on this."
  },
  {
    "id": "28",
    "employee_id": "8",
    "title": "Good collaboration with team",
    "content": "Great teamwork",
    "category": "behavior",
    "status": "pending_response",
    "created_at": "2025-12-03T15:49:27.146671",
    "updated_at": "2025-12-03T15:49:27.146671"
  }
]